salesgpt/__init__.py
salesgpt/agents.py
salesgpt/chains.py
salesgpt/custom_invoke.py
salesgpt/logger.py
salesgpt/parsers.py
salesgpt/prompts.py
salesgpt/prompts_cn.py
salesgpt/salesgptapi.py
salesgpt/stages.py
salesgpt/templates.py
salesgpt/tools.py
salesgpt/version.py
salesgpt-0.1.2.dist-info/LICENSE
salesgpt-0.1.2.dist-info/METADATA
salesgpt-0.1.2.dist-info/WHEEL
salesgpt-0.1.2.dist-info/RECORD
