Metadata-Version: 2.1
Name: SalesGPT
Version: 0.1.2
Summary: SalesGPT - Your Context-Aware AI Sales Assistant
Home-page: https://github.com/filip-michalsky/SalesGPT
License: Apache-2.0
Keywords: openai,sales,gpt,autonomous,agi
Author: Filip Michalsky 
Requires-Python: >=3.8.1,<4.0.0
Classifier: Development Status :: 4 - Beta
Classifier: Intended Audience :: Developers
Classifier: License :: OSI Approved :: Apache Software License
Classifier: Programming Language :: Python :: 3
Classifier: Programming Language :: Python :: 3.9
Classifier: Programming Language :: Python :: 3.10
Classifier: Programming Language :: Python :: 3.11
Classifier: Programming Language :: Python :: 3 :: Only
Classifier: Programming Language :: Python :: 3.8
Classifier: Topic :: Scientific/Engineering :: Artificial Intelligence
Requires-Dist: chromadb (>=0.4.18,<0.5.0)
Requires-Dist: ipykernel (>=6.27.1,<7.0.0)
Requires-Dist: langchain (==0.1.0)
Requires-Dist: langchain-openai (==0.0.2)
Requires-Dist: litellm (>=1.10.2,<2.0.0)
Requires-Dist: openai (==1.7.0)
Requires-Dist: pydantic (>=2.5.2,<3.0.0)
Requires-Dist: pytest (>=7.4.3,<8.0.0)
Requires-Dist: pytest-asyncio (>=0.23.1,<0.24.0)
Requires-Dist: pytest-cov (>=4.1.0,<5.0.0)
Requires-Dist: tiktoken (>=0.5.2,<0.6.0)
Project-URL: Repository, https://github.com/filip-michalsky/SalesGPT
